<suitelet scriptid="customscript_mhi_stripe_generate_link_su">
  <description></description>
  <isinactive>F</isinactive>
  <name>MHI Stripe Payment Generate Link SU</name>
  <notifyadmins>F</notifyadmins>
  <notifyemails></notifyemails>
  <notifyowner>T</notifyowner>
  <notifyuser>F</notifyuser>
  <scriptfile>[/SuiteScripts/MHI/PaymentLink/MHI_Stripe_Payment_Generate_Link_SU.js]</scriptfile>
  <scriptdeployments>
    <scriptdeployment scriptid="customdeploy_mhi_stripe_generate_link_su">
      <allemployees>F</allemployees>
      <allpartners>F</allpartners>
      <allroles>T</allroles>
      <audslctrole></audslctrole>
      <eventtype></eventtype>
      <isdeployed>T</isdeployed>
      <isonline>F</isonline>
      <loglevel>DEBUG</loglevel>
      <runasrole>ADMINISTRATOR</runasrole>
      <status>RELEASED</status>
      <title>MHI Stripe Payment Generate Link SU</title>
    </scriptdeployment>
  </scriptdeployments>
</suitelet>
